MANIFEST.in
README.rst
requirements.txt
setup.cfg
setup.py
pymessenger2/__init__.py
pymessenger2/airline.py
pymessenger2/bot.py
pymessenger2/buttons.py
pymessenger2/utils.py
pymessenger2.egg-info/PKG-INFO
pymessenger2.egg-info/SOURCES.txt
pymessenger2.egg-info/dependency_links.txt
pymessenger2.egg-info/requires.txt
pymessenger2.egg-info/top_level.txt