Metadata-Version: 1.1
Name: pymessenger2
Version: 3.1.0
Summary: Python Wrapper for Facebook Messenger Platform
Home-page: https://github.com/Cretezy/pymessenger2
Author: Charles Crete
Author-email: charles@cretezy.com
License: MIT
Download-URL: https://github.com/Cretezy/pymessenger2/archive/v3.1.0.tar.gz
Keywords: facebook messenger,python,wrapper,bot,messenger bot
Platform: UNKNOWN
